aarc_g002_entitlement/__init__.py
aarc_g002_entitlement/test_entitlement.py
aarc_g002_entitlement-0.3.2.dist-info/LICENSE
aarc_g002_entitlement-0.3.2.dist-info/METADATA
aarc_g002_entitlement-0.3.2.dist-info/WHEEL
aarc_g002_entitlement-0.3.2.dist-info/pbr.json
aarc_g002_entitlement-0.3.2.dist-info/top_level.txt
aarc_g002_entitlement-0.3.2.dist-info/RECORD
