Metadata-Version: 2.1
Name: aarc-g002-entitlement
Version: 0.3.2
Summary: Parse and compare entitlements according to the AARC-G002 recommendation (https://aarc-community.org/guidelines/aarc-g002)
Home-page: https://github.com/kit-scc/aarc-g002-entitlement
Author: Marcus Hardt
Author-email: hardt@kit.edu
License: MIT
Project-URL: Bug Tracker, https://github.com/kit-scc/aarc-g002-entitlement/issues
Project-URL: Documentation, https://aarc-g002-entitlement.readthedocs.io/en/latest/
Platform: UNKNOWN
Classifier: Development Status :: 3 - Alpha
Classifier: Environment :: Console
Classifier: Environment :: Web Environment
Classifier: Intended Audience :: Developers
Classifier: Intended Audience :: Information Technology
Classifier: Intended Audience :: Science/Research
Classifier: Intended Audience :: System Administrators
Classifier: License :: OSI Approved :: MIT License
Classifier: Operating System :: OS Independent
Classifier: Natural Language :: English
Classifier: Programming Language :: Python
Classifier: Programming Language :: Python :: 2
Classifier: Programming Language :: Python :: 3
Classifier: Topic :: System :: Systems Administration
Classifier: Topic :: System :: Systems Administration :: Authentication/Directory
Classifier: Topic :: Utilities
License-File: LICENSE
Requires-Dist: regex
